docs/conf.py
docs/source/conf.py
enspara/__init__.py
enspara/exception.py
enspara/apps/__init__.py
enspara/apps/cluster.py
enspara/apps/collect_cards.py
enspara/apps/compute-shannon-entropy.py
enspara/apps/implied_timescales.py
enspara/apps/main.py
enspara/apps/reassign.py
enspara/apps/smFRET_dye_MC.py
enspara/apps/smFRET_point_clouds.py
enspara/apps/util.py
enspara/cards/__init__.py
enspara/cards/cards.py
enspara/cards/disorder.py
enspara/cards/featurizers.py
enspara/citation/__init__.py
enspara/citation/citation.py
enspara/cluster/__init__.py
enspara/cluster/hybrid.py
enspara/cluster/kcenters.py
enspara/cluster/kmedoids.py
enspara/cluster/save_states.py
enspara/cluster/util.py
enspara/data/dyes/point-clouds/make_point_clouds.py
enspara/geometry/__init__.py
enspara/geometry/dye_lifetimes.py
enspara/geometry/dyes_from_expt_dist.py
enspara/geometry/explicit_r0_calc.py
enspara/geometry/helix.py
enspara/geometry/libdist.c
enspara/geometry/libdist.cpython-312-darwin.so
enspara/geometry/libdist.pyx
enspara/geometry/pockets.py
enspara/geometry/rmsf.py
enspara/geometry/rotamer.py
enspara/info_theory/__init__.py
enspara/info_theory/entropy.py
enspara/info_theory/exposons.py
enspara/info_theory/libinfo.c
enspara/info_theory/libinfo.cpython-312-darwin.so
enspara/info_theory/libinfo.pyx
enspara/info_theory/mutual_info.py
enspara/mpi/__init__.py
enspara/mpi/io.py
enspara/mpi/ops.py
enspara/mpi/util.py
enspara/msm/__init__.py
enspara/msm/bace.py
enspara/msm/bootstrap.py
enspara/msm/builders.py
enspara/msm/libmsm.c
enspara/msm/libmsm.cpython-312-darwin.so
enspara/msm/libmsm.pyx
enspara/msm/msm.py
enspara/msm/synthetic_data.py
enspara/msm/timescales.py
enspara/msm/transition_matrices.py
enspara/ra/__init__.py
enspara/ra/ra.py
enspara/test/__init__.py
enspara/test/msm_data.py
enspara/test/test_apps_cluster.py
enspara/test/test_apps_cluster_mpi.py
enspara/test/test_apps_implied_timescales.py
enspara/test/test_apps_reassign.py
enspara/test/test_bace.py
enspara/test/test_cards.py
enspara-0.3.1.dist-info/licenses/LICENSE
enspara-0.3.1.dist-info/METADATA
enspara-0.3.1.dist-info/WHEEL
enspara-0.3.1.dist-info/entry_points.txt
enspara-0.3.1.dist-info/top_level.txt
enspara-0.3.1.dist-info/RECORD
