Metadata-Version: 2.4
Name: enspara
Version: 0.3.1
Summary: Tools for ensemble modeling
Author: J. R. Porter, M. I. Zimmerman
Author-email: "G. R. Bowman" <grbowman@seas.upenn.edu>
License-Expression: GPL-3.0-or-later
Project-URL: Homepage, https://enspara.readthedocs.io/
Project-URL: Documentation, https://enspara.readthedocs.io/
Project-URL: Repository, https://github.com/bowman-lab/enspara
Project-URL: Bug Tracker, https://github.com/bowman-lab/enspara/issues
Project-URL: Changelog, https://github.com/bowman-lab/enspara/releases
Classifier: Development Status :: 3 - Alpha
Classifier: Intended Audience :: Science/Research
Classifier: Intended Audience :: Developers
Classifier: Programming Language :: Cython
Classifier: Programming Language :: Python :: 3 :: Only
Classifier: Topic :: Scientific/Engineering :: Bio-Informatics
Classifier: Topic :: Scientific/Engineering :: Chemistry
Classifier: Operating System :: POSIX
Classifier: Operating System :: Unix
Classifier: Operating System :: MacOS
Requires-Python: >=3.11
License-File: LICENSE
Requires-Dist: Cython>=0.24
Requires-Dist: numpy>=2.3.0
Requires-Dist: tables>=3.2
Requires-Dist: matplotlib>=1.5.1
Requires-Dist: mdtraj>=1.7
Requires-Dist: psutil>=5.2.2
Requires-Dist: pandas
Requires-Dist: scikit-learn>=0.23.2
Requires-Dist: scipy>=0.17
Requires-Dist: pyyaml
Provides-Extra: dev
Requires-Dist: pytest; extra == "dev"
Provides-Extra: docs
Requires-Dist: Sphinx>=2.3.0; extra == "docs"
Requires-Dist: sphinx-rtd-theme>=0.4.3; extra == "docs"
Requires-Dist: sphinxcontrib-websupport>=1.1.2; extra == "docs"
Requires-Dist: numpydoc>=0.9.1; extra == "docs"
Provides-Extra: mpi
Requires-Dist: mpi4py>=2.0.0; extra == "mpi"
Dynamic: license-file
